README.md
pyproject.toml
setup.cfg
setup.py
rubiCipherX/__init__.py
rubiCipherX/client.py
rubiCipherX.egg-info/PKG-INFO
rubiCipherX.egg-info/SOURCES.txt
rubiCipherX.egg-info/dependency_links.txt
rubiCipherX.egg-info/requires.txt
rubiCipherX.egg-info/top_level.txt
rubiCipherX/crypto/__init__.py
rubiCipherX/crypto/crypto.py
rubiCipherX/gadgets/__init__.py
rubiCipherX/gadgets/classino.py
rubiCipherX/gadgets/exceptions.py
rubiCipherX/gadgets/methods.py
rubiCipherX/network/__init__.py
rubiCipherX/network/connection.py
rubiCipherX/network/proxies.py
rubiCipherX/sessions/__init__.py
rubiCipherX/sessions/sqliteSession.py
rubiCipherX/sessions/stringSession.py
rubiCipherX/structs/__init__.py
rubiCipherX/structs/handlers.py
rubiCipherX/structs/models.py
rubiCipherX/structs/results.py
rubiCipherX/structs/struct.py