Metadata-Version: 2.1
Name: rubiCipherX
Version: 0.1
Summary: Rubika Lib python3
Home-page: https://github.com/CipherX-B4ar3/rubikaLib
License: UNKNOWN
Platform: UNKNOWN
Requires-Python: >=3.9
